[
	{
		"id": "oSOX6wB0zjwIl_rbNdFbq/1701424795126",
		"image": "https://s2.loli.net/2023/12/01/9OKJL7jlbXgocTZ.png",
		"loading": false,
		"createTime": "2023-12-01"
	},
	{
		"id": "e6e-HhsDGvA94R9wD_kUW/1701424795126",
		"image": "https://s2.loli.net/2023/12/01/9jSd8G1PBDQVyLZ.png",
		"loading": false,
		"createTime": "2023-12-01"
	},
	{
		"id": "qW_xaFi4-FWIBxSGyClpl/1701424795125",
		"image": "https://s2.loli.net/2023/12/01/ydGILCvQMRNt7uV.png",
		"loading": false,
		"createTime": "2023-12-01"
	},
	{
		"id": "_K5ZFmZuBw3Tn0WXr-6QD/1701424795125",
		"image": "https://s2.loli.net/2023/12/01/fBXNzZHw8uR7v54.png",
		"loading": false,
		"createTime": "2023-12-01"
	},
	{
		"id": "BMm_q_UiwrpaIEc0w-75o/1701424795124",
		"image": "https://s2.loli.net/2023/12/01/UBbIgunCrXylS3z.png",
		"loading": false,
		"createTime": "2023-12-01"
	}
]